[ {
  "name" : "Fmp - BC Dubai",
  "time" : "17:00",
  "detailUrl" : "https://istatistik.nesine.com/2445586",
  "odds" : {
    "ms1" : 2.87,
    "ms2" : 1.14,
    "h1Value" : 6.5,
    "h2Value" : 0.0,
    "h1" : 1.68,
    "h2" : 1.59,
    "hOverUnderValue" : 166.5,
    "over" : 1.65,
    "under" : 1.62
  },
  "index" : 0
}, {
  "name" : "Olimp Ljubljana - Kızıl Yıldız",
  "time" : "19:00",
  "detailUrl" : "https://istatistik.nesine.com/2445533",
  "odds" : {
    "ms1" : 1.79,
    "ms2" : 1.5,
    "h1Value" : 1.5,
    "h2Value" : 0.0,
    "h1" : 1.69,
    "h2" : 1.58,
    "hOverUnderValue" : 171.5,
    "over" : 1.66,
    "under" : 1.6
  },
  "index" : 1
}, {
  "name" : "Darüşşafaka - CO Basketbol",
  "time" : "20:00",
  "detailUrl" : "https://istatistik.nesine.com/2523890",
  "odds" : {
    "ms1" : 1.26,
    "ms2" : 2.32,
    "h1Value" : 0.0,
    "h2Value" : 0.0,
    "h1" : 0.0,
    "h2" : 0.0,
    "hOverUnderValue" : 0.0,
    "over" : 0.0,
    "under" : 0.0
  },
  "index" : 2
}, {
  "name" : "BK Olomoucko - Furnir Dubrava",
  "time" : "20:00",
  "detailUrl" : "https://istatistik.nesine.com/2445592",
  "odds" : {
    "ms1" : 1.72,
    "ms2" : 1.56,
    "h1Value" : 1.5,
    "h2Value" : 0.0,
    "h1" : 1.62,
    "h2" : 1.65,
    "hOverUnderValue" : 164.5,
    "over" : 1.64,
    "under" : 1.63
  },
  "index" : 3
}, {
  "name" : "Rasta Vechta - Oldenburg",
  "time" : "20:30",
  "detailUrl" : "https://istatistik.nesine.com/2476572",
  "odds" : {
    "ms1" : 1.2,
    "ms2" : 2.55,
    "h1Value" : 0.0,
    "h2Value" : 5.5,
    "h1" : 1.59,
    "h2" : 1.68,
    "hOverUnderValue" : 168.5,
    "over" : 1.63,
    "under" : 1.64
  },
  "index" : 4
}, {
  "name" : "Latina - Virtus Gvm Roma 1960",
  "time" : "21:00",
  "detailUrl" : "https://istatistik.nesine.com/2445603",
  "odds" : {
    "ms1" : 1.42,
    "ms2" : 1.92,
    "h1Value" : 0.0,
    "h2Value" : 2.5,
    "h1" : 1.6,
    "h2" : 1.67,
    "hOverUnderValue" : 151.5,
    "over" : 1.65,
    "under" : 1.61
  },
  "index" : 5
}, {
  "name" : "KFUM Nassjo - Boras",
  "time" : "21:04",
  "detailUrl" : "https://istatistik.nesine.com/2445567",
  "odds" : {
    "ms1" : 3.19,
    "ms2" : 1.1,
    "h1Value" : 7.5,
    "h2Value" : 0.0,
    "h1" : 1.64,
    "h2" : 1.63,
    "hOverUnderValue" : 176.5,
    "over" : 1.64,
    "under" : 1.63
  },
  "index" : 6
}, {
  "name" : "Alba Berlin - SC Jena",
  "time" : "22:00",
  "detailUrl" : "https://istatistik.nesine.com/2476571",
  "odds" : {
    "ms1" : 0.0,
    "ms2" : 4.75,
    "h1Value" : 0.0,
    "h2Value" : 11.5,
    "h1" : 1.69,
    "h2" : 1.58,
    "hOverUnderValue" : 168.5,
    "over" : 1.66,
    "under" : 1.6
  },
  "index" : 7
}, {
  "name" : "Treviso - Virtus Bologna",
  "time" : "22:00",
  "detailUrl" : "https://istatistik.nesine.com/2443466",
  "odds" : {
    "ms1" : 3.09,
    "ms2" : 1.11,
    "h1Value" : 7.5,
    "h2Value" : 0.0,
    "h1" : 1.64,
    "h2" : 1.63,
    "hOverUnderValue" : 168.5,
    "over" : 1.62,
    "under" : 1.65
  },
  "index" : 8
} ]