[ {
  "homeTeam" : "Michigan St.",
  "awayTeam" : "N.Carolina",
  "homeStats" : {
    "avgPointsFor" : 80.66666666666667,
    "avgPointsAgainst" : 62.166666666666664,
    "avgTotalPoints" : 142.83333333333334,
    "ppg" : 2.0,
    "empty" : false
  },
  "awayStats" : {
    "avgPointsFor" : 87.5,
    "avgPointsAgainst" : 64.33333333333333,
    "avgTotalPoints" : 151.83333333333334,
    "ppg" : 2.0,
    "empty" : false
  },
  "odds" : {
    "ms1" : 0.0,
    "ms2" : 0.0,
    "h1Value" : 0.0,
    "h2Value" : 0.0,
    "h1" : 0.0,
    "h2" : 0.0,
    "hOverUnderValue" : 0.0,
    "over" : 0.0,
    "under" : 0.0
  },
  "avgPointsForHome" : 75.5,
  "avgPointsForAway" : 83.5,
  "h2hAvgTotalPoints" : 159.0
}, {
  "homeTeam" : "Küba",
  "awayTeam" : "Arjantin",
  "homeStats" : {
    "avgPointsFor" : 76.5,
    "avgPointsAgainst" : 75.0,
    "avgTotalPoints" : 151.5,
    "ppg" : 1.5,
    "empty" : false
  },
  "awayStats" : {
    "avgPointsFor" : 75.5,
    "avgPointsAgainst" : 71.0,
    "avgTotalPoints" : 146.5,
    "ppg" : 1.5,
    "empty" : false
  },
  "odds" : {
    "ms1" : 14.5,
    "ms2" : 0.0,
    "h1Value" : 23.5,
    "h2Value" : 0.0,
    "h1" : 1.7,
    "h2" : 1.58,
    "hOverUnderValue" : 153.5,
    "over" : 1.63,
    "under" : 1.64
  },
  "avgPointsForHome" : 65.0,
  "avgPointsForAway" : 102.5,
  "h2hAvgTotalPoints" : 167.5
}, {
  "homeTeam" : "Şili",
  "awayTeam" : "Brezilya",
  "homeStats" : {
    "avgPointsFor" : 86.16666666666667,
    "avgPointsAgainst" : 66.83333333333333,
    "avgTotalPoints" : 153.0,
    "ppg" : 1.6666666666666667,
    "empty" : false
  },
  "awayStats" : {
    "avgPointsFor" : 80.66666666666667,
    "avgPointsAgainst" : 73.0,
    "avgTotalPoints" : 153.66666666666666,
    "ppg" : 1.8333333333333333,
    "empty" : false
  },
  "odds" : {
    "ms1" : 9.26,
    "ms2" : 0.0,
    "h1Value" : 17.5,
    "h2Value" : 0.0,
    "h1" : 1.59,
    "h2" : 1.68,
    "hOverUnderValue" : 150.5,
    "over" : 1.61,
    "under" : 1.65
  },
  "avgPointsForHome" : 56.4,
  "avgPointsForAway" : 84.2,
  "h2hAvgTotalPoints" : 140.6
}, {
  "homeTeam" : "Panama",
  "awayTeam" : "Uruguay",
  "homeStats" : {
    "avgPointsFor" : 70.5,
    "avgPointsAgainst" : 84.0,
    "avgTotalPoints" : 154.5,
    "ppg" : 1.3333333333333333,
    "empty" : false
  },
  "awayStats" : {
    "avgPointsFor" : 83.33333333333333,
    "avgPointsAgainst" : 78.33333333333333,
    "avgTotalPoints" : 161.66666666666666,
    "ppg" : 1.5,
    "empty" : false
  },
  "odds" : {
    "ms1" : 1.23,
    "ms2" : 2.41,
    "h1Value" : 0.0,
    "h2Value" : 5.5,
    "h1" : 1.61,
    "h2" : 1.65,
    "hOverUnderValue" : 157.5,
    "over" : 1.62,
    "under" : 1.65
  },
  "avgPointsForHome" : 72.66666666666667,
  "avgPointsForAway" : 80.33333333333333,
  "h2hAvgTotalPoints" : 153.0
}, {
  "homeTeam" : "Kolombiya",
  "awayTeam" : "Venezuela",
  "homeStats" : {
    "avgPointsFor" : 77.66666666666667,
    "avgPointsAgainst" : 89.5,
    "avgTotalPoints" : 167.16666666666666,
    "ppg" : 1.3333333333333333,
    "empty" : false
  },
  "awayStats" : {
    "avgPointsFor" : 65.33333333333333,
    "avgPointsAgainst" : 78.5,
    "avgTotalPoints" : 143.83333333333334,
    "ppg" : 1.3333333333333333,
    "empty" : false
  },
  "odds" : {
    "ms1" : 1.22,
    "ms2" : 2.46,
    "h1Value" : 0.0,
    "h2Value" : 5.5,
    "h1" : 1.65,
    "h2" : 1.62,
    "hOverUnderValue" : 142.5,
    "over" : 1.61,
    "under" : 1.65
  },
  "avgPointsForHome" : 66.0,
  "avgPointsForAway" : 75.66666666666667,
  "h2hAvgTotalPoints" : 141.66666666666666
}, {
  "homeTeam" : "Avustralya",
  "awayTeam" : "Yeni Zelanda",
  "homeStats" : {
    "avgPointsFor" : 94.33333333333333,
    "avgPointsAgainst" : 70.0,
    "avgTotalPoints" : 164.33333333333334,
    "ppg" : 2.0,
    "empty" : false
  },
  "awayStats" : {
    "avgPointsFor" : 93.16666666666667,
    "avgPointsAgainst" : 84.16666666666667,
    "avgTotalPoints" : 177.33333333333334,
    "ppg" : 1.6666666666666667,
    "empty" : false
  },
  "odds" : {
    "ms1" : 1.08,
    "ms2" : 3.33,
    "h1Value" : 0.0,
    "h2Value" : 8.5,
    "h1" : 1.67,
    "h2" : 1.59,
    "hOverUnderValue" : 169.5,
    "over" : 1.63,
    "under" : 1.64
  },
  "avgPointsForHome" : 88.83333333333333,
  "avgPointsForAway" : 79.5,
  "h2hAvgTotalPoints" : 168.33333333333334
}, {
  "homeTeam" : "Guam",
  "awayTeam" : "Filipinler",
  "homeStats" : {
    "avgPointsFor" : 70.83333333333333,
    "avgPointsAgainst" : 90.83333333333333,
    "avgTotalPoints" : 161.66666666666666,
    "ppg" : 1.3333333333333333,
    "empty" : false
  },
  "awayStats" : {
    "avgPointsFor" : 74.66666666666667,
    "avgPointsAgainst" : 82.66666666666667,
    "avgTotalPoints" : 157.33333333333334,
    "ppg" : 1.1666666666666667,
    "empty" : false
  },
  "odds" : {
    "ms1" : 10.15,
    "ms2" : 0.0,
    "h1Value" : 21.5,
    "h2Value" : 0.0,
    "h1" : 1.68,
    "h2" : 1.59,
    "hOverUnderValue" : 164.5,
    "over" : 1.64,
    "under" : 1.63
  },
  "avgPointsForHome" : 0.0,
  "avgPointsForAway" : 0.0,
  "h2hAvgTotalPoints" : 0.0
}, {
  "homeTeam" : "Woori Bank H",
  "awayTeam" : "Busan BNK S.",
  "homeStats" : {
    "avgPointsFor" : 52.333333333333336,
    "avgPointsAgainst" : 57.166666666666664,
    "avgTotalPoints" : 109.5,
    "ppg" : 1.1666666666666667,
    "empty" : false
  },
  "awayStats" : {
    "avgPointsFor" : 58.166666666666664,
    "avgPointsAgainst" : 56.0,
    "avgTotalPoints" : 114.16666666666667,
    "ppg" : 1.6666666666666667,
    "empty" : false
  },
  "odds" : {
    "ms1" : 1.94,
    "ms2" : 1.41,
    "h1Value" : 3.5,
    "h2Value" : 0.0,
    "h1" : 1.59,
    "h2" : 1.68,
    "hOverUnderValue" : 120.5,
    "over" : 1.6,
    "under" : 1.66
  },
  "avgPointsForHome" : 55.333333333333336,
  "avgPointsForAway" : 54.5,
  "h2hAvgTotalPoints" : 109.83333333333333
}, {
  "homeTeam" : "Japonya",
  "awayTeam" : "Tayvan",
  "homeStats" : {
    "avgPointsFor" : 88.66666666666667,
    "avgPointsAgainst" : 79.33333333333333,
    "avgTotalPoints" : 168.0,
    "ppg" : 1.6666666666666667,
    "empty" : false
  },
  "awayStats" : {
    "avgPointsFor" : 89.16666666666667,
    "avgPointsAgainst" : 77.83333333333333,
    "avgTotalPoints" : 167.0,
    "ppg" : 1.6666666666666667,
    "empty" : false
  },
  "odds" : {
    "ms1" : 0.0,
    "ms2" : 5.24,
    "h1Value" : 0.0,
    "h2Value" : 11.5,
    "h1" : 1.64,
    "h2" : 1.63,
    "hOverUnderValue" : 163.5,
    "over" : 1.59,
    "under" : 1.67
  },
  "avgPointsForHome" : 81.66666666666667,
  "avgPointsForAway" : 65.66666666666667,
  "h2hAvgTotalPoints" : 147.33333333333334
}, {
  "homeTeam" : "T. Excellenc",
  "awayTeam" : "N.Storks",
  "homeStats" : {
    "avgPointsFor" : 90.66666666666667,
    "avgPointsAgainst" : 81.0,
    "avgTotalPoints" : 171.66666666666666,
    "ppg" : 1.6666666666666667,
    "empty" : false
  },
  "awayStats" : {
    "avgPointsFor" : 82.66666666666667,
    "avgPointsAgainst" : 65.5,
    "avgTotalPoints" : 148.16666666666666,
    "ppg" : 2.0,
    "empty" : false
  },
  "odds" : {
    "ms1" : 2.96,
    "ms2" : 1.13,
    "h1Value" : 6.5,
    "h2Value" : 0.0,
    "h1" : 1.65,
    "h2" : 1.62,
    "hOverUnderValue" : 152.5,
    "over" : 1.61,
    "under" : 1.65
  },
  "avgPointsForHome" : 0.0,
  "avgPointsForAway" : 0.0,
  "h2hAvgTotalPoints" : 0.0
}, {
  "homeTeam" : "Çin",
  "awayTeam" : "Güney Kore",
  "homeStats" : {
    "avgPointsFor" : 91.5,
    "avgPointsAgainst" : 78.33333333333333,
    "avgTotalPoints" : 169.83333333333334,
    "ppg" : 1.8333333333333333,
    "empty" : false
  },
  "awayStats" : {
    "avgPointsFor" : 86.66666666666667,
    "avgPointsAgainst" : 81.5,
    "avgTotalPoints" : 168.16666666666666,
    "ppg" : 1.6666666666666667,
    "empty" : false
  },
  "odds" : {
    "ms1" : 0.0,
    "ms2" : 9.35,
    "h1Value" : 0.0,
    "h2Value" : 17.5,
    "h1" : 1.67,
    "h2" : 1.59,
    "hOverUnderValue" : 160.5,
    "over" : 1.61,
    "under" : 1.65
  },
  "avgPointsForHome" : 81.16666666666667,
  "avgPointsForAway" : 78.33333333333333,
  "h2hAvgTotalPoints" : 159.5
}, {
  "homeTeam" : "Y.B. Adaları",
  "awayTeam" : "Güney Sudan",
  "homeStats" : {
    "avgPointsFor" : 80.0,
    "avgPointsAgainst" : 71.83333333333333,
    "avgTotalPoints" : 151.83333333333334,
    "ppg" : 1.6666666666666667,
    "empty" : false
  },
  "awayStats" : {
    "avgPointsFor" : 82.0,
    "avgPointsAgainst" : 66.16666666666667,
    "avgTotalPoints" : 148.16666666666666,
    "ppg" : 1.5,
    "empty" : false
  },
  "odds" : {
    "ms1" : 2.41,
    "ms2" : 1.23,
    "h1Value" : 5.5,
    "h2Value" : 0.0,
    "h1" : 1.6,
    "h2" : 1.67,
    "hOverUnderValue" : 145.5,
    "over" : 1.67,
    "under" : 1.59
  },
  "avgPointsForHome" : 0.0,
  "avgPointsForAway" : 0.0,
  "h2hAvgTotalPoints" : 0.0
}, {
  "homeTeam" : "Libya",
  "awayTeam" : "Kamerun",
  "homeStats" : {
    "avgPointsFor" : 61.0,
    "avgPointsAgainst" : 84.66666666666667,
    "avgTotalPoints" : 145.66666666666666,
    "ppg" : 1.3333333333333333,
    "empty" : false
  },
  "awayStats" : {
    "avgPointsFor" : 80.66666666666667,
    "avgPointsAgainst" : 81.5,
    "avgTotalPoints" : 162.16666666666666,
    "ppg" : 1.3333333333333333,
    "empty" : false
  },
  "odds" : {
    "ms1" : 12.95,
    "ms2" : 0.0,
    "h1Value" : 20.5,
    "h2Value" : 0.0,
    "h1" : 1.66,
    "h2" : 1.6,
    "hOverUnderValue" : 144.5,
    "over" : 1.64,
    "under" : 1.63
  },
  "avgPointsForHome" : 0.0,
  "avgPointsForAway" : 0.0,
  "h2hAvgTotalPoints" : 0.0
}, {
  "homeTeam" : "Slovenya",
  "awayTeam" : "Estonya",
  "homeStats" : {
    "avgPointsFor" : 91.5,
    "avgPointsAgainst" : 87.16666666666667,
    "avgTotalPoints" : 178.66666666666666,
    "ppg" : 1.6666666666666667,
    "empty" : false
  },
  "awayStats" : {
    "avgPointsFor" : 69.0,
    "avgPointsAgainst" : 78.16666666666667,
    "avgTotalPoints" : 147.16666666666666,
    "ppg" : 1.1666666666666667,
    "empty" : false
  },
  "odds" : {
    "ms1" : 1.33,
    "ms2" : 2.13,
    "h1Value" : 0.0,
    "h2Value" : 4.5,
    "h1" : 1.7,
    "h2" : 1.58,
    "hOverUnderValue" : 157.5,
    "over" : 1.59,
    "under" : 1.67
  },
  "avgPointsForHome" : 91.0,
  "avgPointsForAway" : 81.0,
  "h2hAvgTotalPoints" : 172.0
}, {
  "homeTeam" : "Macaristan",
  "awayTeam" : "Finlandiya",
  "homeStats" : {
    "avgPointsFor" : 76.16666666666667,
    "avgPointsAgainst" : 72.33333333333333,
    "avgTotalPoints" : 148.5,
    "ppg" : 1.5,
    "empty" : false
  },
  "awayStats" : {
    "avgPointsFor" : 83.16666666666667,
    "avgPointsAgainst" : 87.83333333333333,
    "avgTotalPoints" : 171.0,
    "ppg" : 1.3333333333333333,
    "empty" : false
  },
  "odds" : {
    "ms1" : 2.55,
    "ms2" : 1.2,
    "h1Value" : 5.5,
    "h2Value" : 0.0,
    "h1" : 1.68,
    "h2" : 1.59,
    "hOverUnderValue" : 158.5,
    "over" : 1.63,
    "under" : 1.64
  },
  "avgPointsForHome" : 0.0,
  "avgPointsForAway" : 0.0,
  "h2hAvgTotalPoints" : 0.0
}, {
  "homeTeam" : "Letonya",
  "awayTeam" : "Hollanda",
  "homeStats" : {
    "avgPointsFor" : 81.83333333333333,
    "avgPointsAgainst" : 78.66666666666667,
    "avgTotalPoints" : 160.5,
    "ppg" : 1.5,
    "empty" : false
  },
  "awayStats" : {
    "avgPointsFor" : 73.66666666666667,
    "avgPointsAgainst" : 74.16666666666667,
    "avgTotalPoints" : 147.83333333333334,
    "ppg" : 1.5,
    "empty" : false
  },
  "odds" : {
    "ms1" : 1.19,
    "ms2" : 2.59,
    "h1Value" : 0.0,
    "h2Value" : 5.5,
    "h1" : 1.58,
    "h2" : 1.7,
    "hOverUnderValue" : 155.5,
    "over" : 1.63,
    "under" : 1.64
  },
  "avgPointsForHome" : 0.0,
  "avgPointsForAway" : 0.0,
  "h2hAvgTotalPoints" : 0.0
}, {
  "homeTeam" : "Hırvatistan",
  "awayTeam" : "G. Kıbrıs",
  "homeStats" : {
    "avgPointsFor" : 95.16666666666667,
    "avgPointsAgainst" : 66.66666666666667,
    "avgTotalPoints" : 161.83333333333334,
    "ppg" : 2.0,
    "empty" : false
  },
  "awayStats" : {
    "avgPointsFor" : 58.333333333333336,
    "avgPointsAgainst" : 97.0,
    "avgTotalPoints" : 155.33333333333334,
    "ppg" : 1.0,
    "empty" : false
  },
  "odds" : {
    "ms1" : 0.0,
    "ms2" : 17.05,
    "h1Value" : 0.0,
    "h2Value" : 31.5,
    "h1" : 1.64,
    "h2" : 1.63,
    "hOverUnderValue" : 156.5,
    "over" : 1.65,
    "under" : 1.61
  },
  "avgPointsForHome" : 98.0,
  "avgPointsForAway" : 65.0,
  "h2hAvgTotalPoints" : 163.0
}, {
  "homeTeam" : "Çekya",
  "awayTeam" : "İsveç",
  "homeStats" : {
    "avgPointsFor" : 73.0,
    "avgPointsAgainst" : 86.83333333333333,
    "avgTotalPoints" : 159.83333333333334,
    "ppg" : 1.1666666666666667,
    "empty" : false
  },
  "awayStats" : {
    "avgPointsFor" : 80.33333333333333,
    "avgPointsAgainst" : 83.83333333333333,
    "avgTotalPoints" : 164.16666666666666,
    "ppg" : 1.1666666666666667,
    "empty" : false
  },
  "odds" : {
    "ms1" : 1.29,
    "ms2" : 2.24,
    "h1Value" : 0.0,
    "h2Value" : 4.5,
    "h1" : 1.61,
    "h2" : 1.65,
    "hOverUnderValue" : 157.5,
    "over" : 1.63,
    "under" : 1.64
  },
  "avgPointsForHome" : 0.0,
  "avgPointsForAway" : 0.0,
  "h2hAvgTotalPoints" : 0.0
}, {
  "homeTeam" : "Fransa",
  "awayTeam" : "Belçika",
  "homeStats" : {
    "avgPointsFor" : 88.5,
    "avgPointsAgainst" : 78.5,
    "avgTotalPoints" : 167.0,
    "ppg" : 1.6666666666666667,
    "empty" : false
  },
  "awayStats" : {
    "avgPointsFor" : 70.5,
    "avgPointsAgainst" : 79.33333333333333,
    "avgTotalPoints" : 149.83333333333334,
    "ppg" : 1.3333333333333333,
    "empty" : false
  },
  "odds" : {
    "ms1" : 0.0,
    "ms2" : 5.13,
    "h1Value" : 0.0,
    "h2Value" : 11.5,
    "h1" : 1.61,
    "h2" : 1.65,
    "hOverUnderValue" : 153.5,
    "over" : 1.66,
    "under" : 1.6
  },
  "avgPointsForHome" : 80.2,
  "avgPointsForAway" : 60.6,
  "h2hAvgTotalPoints" : 140.8
}, {
  "homeTeam" : "Polonya",
  "awayTeam" : "Avusturya",
  "homeStats" : {
    "avgPointsFor" : 75.33333333333333,
    "avgPointsAgainst" : 75.83333333333333,
    "avgTotalPoints" : 151.16666666666666,
    "ppg" : 1.5,
    "empty" : false
  },
  "awayStats" : {
    "avgPointsFor" : 71.83333333333333,
    "avgPointsAgainst" : 74.83333333333333,
    "avgTotalPoints" : 146.66666666666666,
    "ppg" : 1.3333333333333333,
    "empty" : false
  },
  "odds" : {
    "ms1" : 0.0,
    "ms2" : 7.1,
    "h1Value" : 0.0,
    "h2Value" : 14.5,
    "h1" : 1.65,
    "h2" : 1.62,
    "hOverUnderValue" : 156.5,
    "over" : 1.63,
    "under" : 1.64
  },
  "avgPointsForHome" : 85.0,
  "avgPointsForAway" : 72.75,
  "h2hAvgTotalPoints" : 157.75
} ]