[ {
  "algorithm" : "BasketEnsembleModel",
  "homeTeam" : "Chicago",
  "awayTeam" : "New Orleans",
  "pHome" : 0.6729008684540048,
  "pDraw" : 0.0,
  "pAway" : 0.32709913154599524,
  "pOver25" : 0.41301129454092234,
  "pBttsYes" : 0.0,
  "pick" : "MS1 | Alt",
  "confidence" : 0.6942768821154839,
  "scoreline" : "124-121"
}, {
  "algorithm" : "BasketEnsembleModel",
  "homeTeam" : "San Antonio",
  "awayTeam" : "New York",
  "pHome" : 0.8103652537805319,
  "pDraw" : 0.0,
  "pAway" : 0.18963474621946813,
  "pOver25" : 0.5981939506375115,
  "pBttsYes" : 0.0,
  "pick" : "MS1 | Üst",
  "confidence" : 0.840867743481102,
  "scoreline" : "123-116"
}, {
  "algorithm" : "BasketEnsembleModel",
  "homeTeam" : "Toronto",
  "awayTeam" : "Denver",
  "pHome" : 0.5405664983708566,
  "pDraw" : 0.0,
  "pAway" : 0.4594335016291434,
  "pOver25" : 0.6107870493792429,
  "pBttsYes" : 0.0,
  "pick" : "Yakın | Üst",
  "confidence" : 0.6147147718057443,
  "scoreline" : "117-116"
}, {
  "algorithm" : "BasketEnsembleModel",
  "homeTeam" : "Milwaukee",
  "awayTeam" : "Washington",
  "pHome" : 0.6805951563497645,
  "pDraw" : 0.0,
  "pAway" : 0.31940484365023547,
  "pOver25" : 0.3475506079034917,
  "pBttsYes" : 0.0,
  "pick" : "MS1 | Alt",
  "confidence" : 0.702755799401274,
  "scoreline" : "117-113"
}, {
  "algorithm" : "BasketEnsembleModel",
  "homeTeam" : "Oklahoma",
  "awayTeam" : "Portland",
  "pHome" : 0.7855016042427456,
  "pDraw" : 0.0,
  "pAway" : 0.21449839575725438,
  "pOver25" : 0.36727301264762463,
  "pBttsYes" : 0.0,
  "pick" : "MS1 | Alt",
  "confidence" : 0.8109778921269089,
  "scoreline" : "117-111"
}, {
  "algorithm" : "BasketEnsembleModel",
  "homeTeam" : "Goyang",
  "awayTeam" : "Daegu PEG.",
  "pHome" : 0.5875492234343813,
  "pDraw" : 0.0,
  "pAway" : 0.4124507765656187,
  "pOver25" : 0.6262782460927947,
  "pBttsYes" : 0.0,
  "pick" : "MS1 | Üst",
  "confidence" : 0.6211017207070073,
  "scoreline" : "80-79"
}, {
  "algorithm" : "BasketEnsembleModel",
  "homeTeam" : "SK Knights",
  "awayTeam" : "Anyang KGC",
  "pHome" : 0.7612272274371987,
  "pDraw" : 0.0,
  "pAway" : 0.23877277256280133,
  "pOver25" : 0.5951052979373426,
  "pBttsYes" : 0.0,
  "pick" : "MS1 | Üst",
  "confidence" : 0.7821467992332648,
  "scoreline" : "78-72"
}, {
  "algorithm" : "BasketEnsembleModel",
  "homeTeam" : "Brisbane B.",
  "awayTeam" : "Perth W.",
  "pHome" : 0.37038161359196203,
  "pDraw" : 0.0,
  "pAway" : 0.629618386408038,
  "pOver25" : 0.45721999984420325,
  "pBttsYes" : 0.0,
  "pick" : "MS2 | Sınırda",
  "confidence" : 0.6564950346068292,
  "scoreline" : "86-89"
}, {
  "algorithm" : "BasketEnsembleModel",
  "homeTeam" : "Zhejiang G.B",
  "awayTeam" : "Qingdao E.",
  "pHome" : 0.5044226260876679,
  "pDraw" : 0.0,
  "pAway" : 0.49557737391233214,
  "pOver25" : 0.4209100925736968,
  "pBttsYes" : 0.0,
  "pick" : "Yakın | Alt",
  "confidence" : 0.5535382933191826,
  "scoreline" : "88-87"
}, {
  "algorithm" : "BasketEnsembleModel",
  "homeTeam" : "Beijing D.",
  "awayTeam" : "Guandong S.T",
  "pHome" : 0.8151018086800546,
  "pDraw" : 0.0,
  "pAway" : 0.1848981913199455,
  "pOver25" : 0.494386820227144,
  "pBttsYes" : 0.0,
  "pick" : "MS1 | Sınırda",
  "confidence" : 0.846734849055201,
  "scoreline" : "93-86"
}, {
  "algorithm" : "BasketEnsembleModel",
  "homeTeam" : "Sichuan B.W.",
  "awayTeam" : "Fujian Stur.",
  "pHome" : 0.23676596271599304,
  "pDraw" : 0.0,
  "pAway" : 0.763234037284007,
  "pOver25" : 0.391918169410835,
  "pBttsYes" : 0.0,
  "pick" : "MS2 | Alt",
  "confidence" : 0.7979388658793545,
  "scoreline" : "80-85"
}, {
  "algorithm" : "BasketEnsembleModel",
  "homeTeam" : "Tianjin P.",
  "awayTeam" : "Zhejiang G.L",
  "pHome" : 0.25094065057080756,
  "pDraw" : 0.0,
  "pAway" : 0.7490593494291924,
  "pOver25" : 0.5459222812133382,
  "pBttsYes" : 0.0,
  "pick" : "MS2 | Sınırda",
  "confidence" : 0.7724739307233665,
  "scoreline" : "87-93"
}, {
  "algorithm" : "BasketEnsembleModel",
  "homeTeam" : "Jiangsu D.",
  "awayTeam" : "Ningbo R.",
  "pHome" : 0.29276962412611207,
  "pDraw" : 0.0,
  "pAway" : 0.7072303758738879,
  "pOver25" : 0.4729876958014495,
  "pBttsYes" : 0.0,
  "pick" : "MS2 | Sınırda",
  "confidence" : 0.7285398470521154,
  "scoreline" : "85-89"
}, {
  "algorithm" : "BasketEnsembleModel",
  "homeTeam" : "Slam Stal",
  "awayTeam" : "Trefl Sopot",
  "pHome" : 0.6227030447747759,
  "pDraw" : 0.0,
  "pAway" : 0.37729695522522405,
  "pOver25" : 0.43567296226488433,
  "pBttsYes" : 0.0,
  "pick" : "MS1 | Alt",
  "confidence" : 0.6502079081600756,
  "scoreline" : "88-85"
} ]